bicscan_engine/__init__.py
bicscan_engine/engine/bytecode_checker.py
bicscan_engine/engine/checklist.py
bicscan_engine/engine/config.py
bicscan_engine/engine/contract_identifier.py
bicscan_engine/engine/get_proxy_contract.py
bicscan_engine/engine/scan_token.py
bicscan_engine/engine/schemas.py
bicscan_engine/engine/trust_verifier_checker.py
bicscan_engine/engine/util.py
bicscan_engine/engine/web3_provider.py
bicscan_engine-0.1.2.dist-info/METADATA
bicscan_engine-0.1.2.dist-info/WHEEL
bicscan_engine-0.1.2.dist-info/RECORD
